LICENSE
README.md
setup.cfg
setup.py
tests/test_couchdb.py
tests/test_mem.py
tests/test_valkey.py
whee/__init__.py
whee/base.py
whee/mem.py
whee/couchdb/__init__.py
whee/valkey/__init__.py
wheepy.egg-info/PKG-INFO
wheepy.egg-info/SOURCES.txt
wheepy.egg-info/dependency_links.txt
wheepy.egg-info/requires.txt
wheepy.egg-info/top_level.txt